Metadata-Version: 2.1
Name: ocrp
Version: 0.1.9.8
Summary: a parser for AWS and Azure ocr json files
Author: Ross Ashman
